aws4/__init__.py
aws4/client.py
aws4/key_pair.py
aws4/py.typed
auth_aws4-0.1.12.dist-info/METADATA
auth_aws4-0.1.12.dist-info/WHEEL
auth_aws4-0.1.12.dist-info/RECORD
