Metadata-Version: 2.4
Name: auth-aws4
Version: 0.1.12
Summary: Usecase agnostic implementation of AWS4 signing schema.
Project-URL: homepage, https://github.com/NRWLDev/auth-aws4/
Project-URL: documentation, https://nrwldev.github.io/auth-aws4/
Author-email: Daniel Edgecombe <daniel@nrwl.co>
Maintainer-email: Daniel Edgecombe <daniel@nrwl.co>
License-Expression: Apache-2.0
Keywords: authorization,aws,signing
Classifier: Development Status :: 1 - Planning
Classifier: Environment :: Web Environment
Classifier: Intended Audience :: Developers
Classifier: License :: OSI Approved :: Apache Software License
Classifier: Operating System :: OS Independent
Classifier: Programming Language :: Python
Classifier: Programming Language :: Python :: 3
Classifier: Programming Language :: Python :: 3 :: Only
Classifier: Programming Language :: Python :: 3.8
Classifier: Programming Language :: Python :: 3.9
Classifier: Programming Language :: Python :: 3.10
Classifier: Programming Language :: Python :: 3.11
Classifier: Programming Language :: Python :: 3.12
Classifier: Topic :: Internet
Requires-Python: >=3.8
Requires-Dist: python-dateutil>=2.0.0
Provides-Extra: dev
Requires-Dist: changelog-gen>=0.12; extra == 'dev'
Requires-Dist: coverage==7.4.3; extra == 'dev'
Requires-Dist: freezegun>=1.2.1; extra == 'dev'
Requires-Dist: multidict>=4.0; extra == 'dev'
Requires-Dist: pre-commit>=3.0.2; extra == 'dev'
Requires-Dist: pytest-cov>=5.0.0; extra == 'dev'
Requires-Dist: pytest-random-order>=1.1.0; extra == 'dev'
Requires-Dist: pytest>=8.2.0; extra == 'dev'
Requires-Dist: ruff>=0.6.4; extra == 'dev'
